tptapi/__init__.py
tptapi/__version__.py
tptapi/client.py
tptapi/errors.py
tptapi-1.1.0.dist-info/DESCRIPTION.rst
tptapi-1.1.0.dist-info/METADATA
tptapi-1.1.0.dist-info/RECORD
tptapi-1.1.0.dist-info/WHEEL
tptapi-1.1.0.dist-info/metadata.json
tptapi-1.1.0.dist-info/top_level.txt
