Metadata-Version: 2.0
Name: tptapi
Version: 1.1.0
Summary: A Python client to interact with powdertoy.co.uk API
Home-page: http://wolfy1339.com/tptapi
Author: wolfy1339
Author-email: webmaster@wolfy1339.com
License: MIT
Platform: UNKNOWN
Classifier: Development Status :: 3 - Alpha
Classifier: Intended Audience :: Developers
Classifier: License :: OSI Approved :: MIT License
Classifier: Natural Language :: English
Classifier: Programming Language :: Python :: Implementation :: CPython
Classifier: Programming Language :: Python
Classifier: Programming Language :: Python :: 2.7
Classifier: Programming Language :: Python :: 3
Classifier: Programming Language :: Python :: 3.3
Classifier: Programming Language :: Python :: 3.4
Classifier: Programming Language :: Python :: 3.5
Classifier: Programming Language :: Python :: 3.6
Classifier: Topic :: Software Development :: Libraries :: Python Modules
Classifier: Topic :: Internet :: WWW/HTTP
Requires-Python: >=2.7,!=3.0.*,!=3.1.*,!=3.2.*
Requires-Dist: six (>=1.10.0)
Requires-Dist: requests (>=2.12.4)
